[
  {
    "fullName": "Roderick Schumm",
    "available": false,
    "phone": "018-782-1495",
    "email": "Roderick.Wuckert@viasupport.com",
    "profile_image": "https://images.unsplash.com/photo-1528660493888-ab6f4761e036?ixlib=rb-1.2.1&ixid=eyJhcHBfaWQiOjEyMDd9&auto=format&fit=crop&w=1800&q=80"
  },
  {
    "fullName": "Efrain Gaylord",
    "available": false,
    "phone": "018-048-3678",
    "email": "Efrain.Hickle84@viasupport.com",
    "profile_image": "https://images.unsplash.com/photo-1528660493888-ab6f4761e036?ixlib=rb-1.2.1&ixid=eyJhcHBfaWQiOjEyMDd9&auto=format&fit=crop&w=1800&q=80"
  },
  {
    "fullName": "Kimberly Lowe",
    "available": false,
    "phone": "729-075-2127",
    "email": "Kimberly_Orn_long_address@viasupport.com",
    "profile_image": "https://images.unsplash.com/photo-1485217988980-11786ced9454?ixlib=rb-1.2.1&ixid=eyJhcHBfaWQiOjEyMDd9&auto=format&fit=crop&w=1800&q=80"
  },
  {
    "fullName": "Delfina Fritsch",
    "available": true,
    "phone": "768-224-685",
    "email": "Delfina.Deckow@viasupport.com",
    "profile_image": "https://images.unsplash.com/photo-1485217988980-11786ced9454?ixlib=rb-1.2.1&ixid=eyJhcHBfaWQiOjEyMDd9&auto=format&fit=crop&w=1800&q=80"
  },
  {
    "fullName": "Natalia",
    "available": true,
    "phone": "913-062-5749",
    "email": "Natalia10@viasupport.com",
    "profile_image": "https://images.unsplash.com/photo-1485217988980-11786ced9454?ixlib=rb-1.2.1&ixid=eyJhcHBfaWQiOjEyMDd9&auto=format&fit=crop&w=1800&q=80"
  },
  {
    "fullName": "Verla Schroeder",
    "available": true,
    "phone": "+359-496-2656",
    "email": "Verla0@viasupport.com",
    "profile_image": "https://images.unsplash.com/photo-1485217988980-11786ced9454?ixlib=rb-1.2.1&ixid=eyJhcHBfaWQiOjEyMDd9&auto=format&fit=crop&w=1800&q=80"
  },
  {
    "fullName": "Trent Crona   ",
    "available": true,
    "phone": "(740)-703-2676",
    "email": "Trent.Powlowski50@viasupport.com",
    "profile_image": "https://images.unsplash.com/photo-1528660493888-ab6f4761e036?ixlib=rb-1.2.1&ixid=eyJhcHBfaWQiOjEyMDd9&auto=format&fit=crop&w=1800&q=80"
  },
  {
    "fullName": "Jess Krajcik-Smith",
    "available": false,
    "phone": "100-578-2952",
    "email": "Jess.Krajcik @viasupport.com",
    "profile_image": "https://images.unsplash.com/photo-1528660493888-ab6f4761e036?ixlib=rb-1.2.1&ixid=eyJhcHBfaWQiOjEyMDd9&auto=format&fit=crop&w=1800&q=80"
  },
  {
    "fullName": "Allan Williamson",
    "available": false,
    "phone": "266-780-0162",
    "email": "Allan55@viasupport.com",
    "profile_image": "https://images.unsplash.com/photo-1528660493888-ab6f4761e036?ixlib=rb-1.2.1&ixid=eyJhcHBfaWQiOjEyMDd9&auto=format&fit=crop&w=1800&q=80"
  },
  {
    "fullName": "Jordy Bednar",
    "available": false,
    "phone": "(476)-512-3146",
    "email": "Jordy.Spencer66@viasupport.com",
    "profile_image": "https://images.unsplash.com/photo-1528660493888-ab6f4761e036?ixlib=rb-1.2.1&ixid=eyJhcHBfaWQiOjEyMDd9&auto=format&fit=crop&w=1800&q=80"
  },
  {
    "fullName": "Dagmar Brakus",
    "available": true,
    "phone": "362-166-4076",
    "email": "Dagmar-Grant-longest-via-support-email-address@viasupport.com",
    "profile_image": "https://images.unsplash.com/photo-1528660493888-ab6f4761e036?ixlib=rb-1.2.1&ixid=eyJhcHBfaWQiOjEyMDd9&auto=format&fit=crop&w=1800&q=80"
  },
  {
    "fullName": "Marilie Little",
    "available": false,
    "phone": "791-891-8925",
    "email": "marilie.tremblay@viasupport.com  ",
    "profile_image": "https://images.unsplash.com/photo-1485217988980-11786ced9454?ixlib=rb-1.2.1&ixid=eyJhcHBfaWQiOjEyMDd9&auto=format&fit=crop&w=1800&q=80"
  },
  {
    "fullName": "Rylan Tromp",
    "available": false,
    "phone": "481-897-4439",
    "email": "Rylan_Legros@viasupport.com",
    "profile_image": "https://images.unsplash.com/photo-1528660493888-ab6f4761e036?ixlib=rb-1.2.1&ixid=eyJhcHBfaWQiOjEyMDd9&auto=format&fit=crop&w=1800&q=80"
  }
]
